Metadata-Version: 2.1
Name: qiniu-async
Version: 1.0.1
Summary: qiniu_async python library
Home-page: https://github.com/qiniu-async
Author: LiuYue
Author-email: zcxey2911@gmail.com
License: Apache 2.0
Keywords: qiniu,qiniu_async,async
Classifier: Development Status :: 3 - Alpha
Classifier: Intended Audience :: Developers
Classifier: Programming Language :: Python :: 3
Classifier: Programming Language :: Python :: 3.7
Classifier: Programming Language :: Python :: 3.8
Classifier: Programming Language :: Python :: 3.9
Classifier: Programming Language :: Python :: 3.10
Classifier: Programming Language :: Python :: 3 :: Only
Classifier: License :: OSI Approved :: MIT License
Classifier: Operating System :: OS Independent
